itk_hasi-0.2.2.dist-info/RECORD
itk_hasi-0.2.2.dist-info/METADATA
itk_hasi-0.2.2.dist-info/top_level.txt
itk_hasi-0.2.2.dist-info/WHEEL
itk_hasi-0.2.2.dist-info/LICENSE
itk/HASIPython.py
itk/itkLandmarkAtlasSegmentationFilterPython.py
itk/itkSegmentBonesInMicroCTFilterPython.py
itk/_HASIPython.so
itk/Configuration/HASIConfig.py
itk/Configuration/HASI_snake_case.py
