Metadata-Version: 2.1
Name: itk-hasi
Version: 0.2.2
Summary: High-throughput Applications for Skeletal Imaging
Home-page: https://itk.org/
Author: Kitware Medical
Author-email: itk+community@discourse.itk.org
License: Apache
Download-URL: https://github.com/KitwareMedical/HASI
Keywords: ITK InsightToolkit
Platform: UNKNOWN
Classifier: License :: OSI Approved :: Apache Software License
Classifier: Programming Language :: Python
Classifier: Programming Language :: C++
Classifier: Development Status :: 4 - Beta
Classifier: Intended Audience :: Developers
Classifier: Intended Audience :: Education
Classifier: Intended Audience :: Healthcare Industry
Classifier: Intended Audience :: Science/Research
Classifier: Topic :: Scientific/Engineering
Classifier: Topic :: Scientific/Engineering :: Medical Science Apps.
Classifier: Topic :: Scientific/Engineering :: Information Analysis
Classifier: Topic :: Software Development :: Libraries
Classifier: Operating System :: Android
Classifier: Operating System :: Microsoft :: Windows
Classifier: Operating System :: POSIX
Classifier: Operating System :: Unix
Classifier: Operating System :: MacOS
License-File: LICENSE
Requires-Dist: itk (>=5.2.0.post2)
Requires-Dist: itk-boneenhancement (>=0.4.2)
Requires-Dist: itk-ioscanco
Requires-Dist: dwd (>=1.0.1)
